LICENSE
LICENSE.txt
MANIFEST.in
README.md
setup.py
bztt_tool.egg-info/PKG-INFO
bztt_tool.egg-info/SOURCES.txt
bztt_tool.egg-info/dependency_links.txt
bztt_tool.egg-info/requires.txt
bztt_tool.egg-info/top_level.txt
requests/__init__.py
requests/__version__.py
requests/_internal_utils.py
requests/adapters.py
requests/api.py
requests/auth.py
requests/certs.py
requests/compat.py
requests/cookies.py
requests/exceptions.py
requests/help.py
requests/hooks.py
requests/models.py
requests/packages.py
requests/sessions.py
requests/status_codes.py
requests/structures.py
requests/utils.py